fk_constraint/__init__.py
fk_constraint/constraints.py
django_fk_constraint-0.0.1a0.dist-info/METADATA
django_fk_constraint-0.0.1a0.dist-info/WHEEL
django_fk_constraint-0.0.1a0.dist-info/top_level.txt
django_fk_constraint-0.0.1a0.dist-info/RECORD
