Metadata-Version: 2.4
Name: django-fk-constraint
Version: 0.0.1a0
Summary: Constraint implementation for composite foreign keys.
Author-email: Simon Charette <charette.s@gmail.com>
License-Expression: MIT
Project-URL: Homepage, https://github.com/charettes/django-fk-constraint
Classifier: Programming Language :: Python :: 3
Classifier: Operating System :: OS Independent
Requires-Python: >=3.10
